ardlib/__init__.py
ardlib/array.py
ardlib/dictionary.py
ardlib/env.py
ardlib/fs.py
ardlib/machine_info.py
ardlib/period.py
ardlib/process.py
ardlib-0.1.0.dist-info/LICENSE
ardlib-0.1.0.dist-info/WHEEL
ardlib-0.1.0.dist-info/METADATA
ardlib-0.1.0.dist-info/RECORD
