Metadata-Version: 2.1
Name: ardlib
Version: 0.1.0
Summary: ardlib
License: MIT
Author: musangtara
Author-email: musangtara@gmail.com
Requires-Python: >=3.7,<4.0
Classifier: License :: OSI Approved :: MIT License
Classifier: Programming Language :: Python :: 3
Classifier: Programming Language :: Python :: 3.7
Classifier: Programming Language :: Python :: 3.8
Classifier: Programming Language :: Python :: 3.9
